lomen/__init__.py
lomen/cli.py
lomen/registry.py
lomen/adapters/langchain.py
lomen/adapters/mcp.py
lomen/plugins/base.py
lomen/plugins/example_plugin.py
lomen/plugins/blockchain/__init__.py
lomen/plugins/blockchain/chains.json
lomen/plugins/blockchain/tools/blockchain_metadata.py
lomen/plugins/evm_rpc/__init__.py
lomen/plugins/evm_rpc/tools/get_block.py
lomen/plugins/evm_rpc/tools/get_block_number.py
lomen/plugins/oneinch/__init__.py
lomen/plugins/oneinch/tools/get_address_from_domain.py
lomen/plugins/oneinch/tools/get_nfts.py
lomen/plugins/oneinch/tools/get_portfolio.py
lomen/plugins/oneinch/tools/get_profit_and_loss.py
lomen/plugins/oneinch/tools/get_protocol_investments.py
lomen/plugins/oneinch/tools/get_token_info.py
lomen-0.1.3.dist-info/METADATA
lomen-0.1.3.dist-info/WHEEL
lomen-0.1.3.dist-info/entry_points.txt
lomen-0.1.3.dist-info/RECORD
