Metadata-Version: 2.4
Name: lomen
Version: 0.1.3
Summary: Plugin-based framework for blockchain/web3 tools
Project-URL: Homepage, https://github.com/username/lomen
Project-URL: Bug Tracker, https://github.com/username/lomen/issues
Project-URL: Documentation, https://github.com/username/lomen#readme
Author-email: Lomen Development Team <example@example.com>
Classifier: License :: OSI Approved :: MIT License
Classifier: Operating System :: OS Independent
Classifier: Programming Language :: Python :: 3
Classifier: Programming Language :: Python :: 3.10
Requires-Python: >=3.10
Requires-Dist: aiohttp
Requires-Dist: fastapi>=0.115.12
Requires-Dist: langchain
Requires-Dist: langchain-community>=0.3.21
Requires-Dist: langchain-openai>=0.3.12
Requires-Dist: langgraph
Requires-Dist: mcp>=1.6.0
Requires-Dist: pydantic
Requires-Dist: pytest>=8.3.5
Requires-Dist: python-dotenv
Requires-Dist: starlette>=0.46.1
Requires-Dist: uvicorn>=0.34.0
Requires-Dist: web3
Provides-Extra: dev
Requires-Dist: black>=25.1.0; extra == 'dev'
Requires-Dist: pytest-asyncio; extra == 'dev'
Requires-Dist: pytest-cov>=4.1.0; extra == 'dev'
Requires-Dist: pytest-mock; extra == 'dev'
Requires-Dist: pytest>=8.3.5; extra == 'dev'
Requires-Dist: ruff>=0.11.4; extra == 'dev'
